moxfield/__init__.py
moxfield/auth.py
moxfield/decks.py
moxfield/folders.py
moxfield/search.py
moxfield-0.4.3.dist-info/LICENSE
moxfield-0.4.3.dist-info/METADATA
moxfield-0.4.3.dist-info/WHEEL
moxfield-0.4.3.dist-info/top_level.txt
moxfield-0.4.3.dist-info/RECORD
