Metadata-Version: 2.1
Name: moxfield
Version: 0.4.3
Summary: Python bindings for Moxfield
Author: Michael Celani
Author-email: michael.j.celani@gmail.com
Classifier: Programming Language :: Python :: 3
Classifier: License :: OSI Approved :: MIT License
Classifier: Operating System :: OS Independent
Requires-Python: >=3.6
License-File: LICENSE
